LICENSE
README.md
setup.py
colorways/__init__.py
colorways/bezier.py
colorways/blend.py
colorways/conv.py
colorways/css.py
colorways/demos.zip
colorways/dist.py
colorways/gen.py
colorways/internals.py
colorways/makedemos.py
colorways/masterpalette.py
colorways/ryb.py
colorways/sort.py
colorways/theory.py
colorways/util.py
colorways/vars.py
colorways/version.py
colorways/wcag.py
colorways.egg-info/PKG-INFO
colorways.egg-info/SOURCES.txt
colorways.egg-info/dependency_links.txt
colorways.egg-info/not-zip-safe
colorways.egg-info/top_level.txt
colorways/p3/__init__.py
colorways/pals/__init__.py
colorways/pals/brands.py
colorways/pals/orig_brands.py
colorways/pals/select.py
colorways/pals/sports.py
colorways/spectra/__init__.py
colorways/spectra/aesthetic.py
colorways/spectra/cie06ten.py
colorways/spectra/cie06two.py
colorways/spectra/cie06twofine.py
colorways/spectra/cie64ten.py
colorways/spectra/rainbow.py