Metadata-Version: 2.1
Name: colorways
Version: 0.9.3
Summary: A Python library for procedural generation of color palettes, color manipulation, and color analysis.
Home-page: https://github.com/jeremymadea/colorways
Author: Jeremy Madea
Author-email: jdmadea@gmail.com
License: MIT
Platform: UNKNOWN
License-File: LICENSE
